{"id":"..\\node_modules\\axios\\package.json","dependencies":[{"name":"C:\\Users\\Alex\\Documents\\workspace\\roy\\node_modules\\axios\\package.json","includedInParent":true,"mtime":1532251455133},{"name":"C:\\Users\\Alex\\Documents\\workspace\\roy\\package.json","includedInParent":true,"mtime":1532256910577},{"name":"C:\\Users\\Alex\\Documents\\workspace\\roy\\.babelrc","includedInParent":true,"mtime":1532257192283}],"generated":{"js":"module.exports = {\n  \"_args\": [\n    [\n      {\n        \"raw\": \"axios@^0.18.0\",\n        \"scope\": null,\n        \"escapedName\": \"axios\",\n        \"name\": \"axios\",\n        \"rawSpec\": \"^0.18.0\",\n        \"spec\": \">=0.18.0 <0.19.0\",\n        \"type\": \"range\"\n      },\n      \"C:\\\\Users\\\\Alex\\\\Documents\\\\workspace\\\\roy\\\\node_modules\\\\@alife\\\\s-request\"\n    ]\n  ],\n  \"_cnpm_publish_time\": 1519082934151,\n  \"_from\": \"axios@>=0.18.0 <0.19.0\",\n  \"_hasShrinkwrap\": false,\n  \"_id\": \"axios@0.18.0\",\n  \"_inCache\": true,\n  \"_location\": \"/axios\",\n  \"_nodeVersion\": \"6.9.5\",\n  \"_npmOperationalInternal\": {\n    \"host\": \"s3://npm-registry-packages\",\n    \"tmp\": \"tmp/axios_0.18.0_1519082934092_0.24234210178813442\"\n  },\n  \"_npmUser\": {\n    \"name\": \"emilyemorehouse\",\n    \"email\": \"emilyemorehouse@gmail.com\"\n  },\n  \"_npmVersion\": \"3.10.10\",\n  \"_phantomChildren\": {},\n  \"_requested\": {\n    \"raw\": \"axios@^0.18.0\",\n    \"scope\": null,\n    \"escapedName\": \"axios\",\n    \"name\": \"axios\",\n    \"rawSpec\": \"^0.18.0\",\n    \"spec\": \">=0.18.0 <0.19.0\",\n    \"type\": \"range\"\n  },\n  \"_requiredBy\": [\n    \"/@alife/s-request\"\n  ],\n  \"_resolved\": \"http://registry.npm.alibaba-inc.com/axios/download/axios-0.18.0.tgz\",\n  \"_shasum\": \"32d53e4851efdc0a11993b6cd000789d70c05102\",\n  \"_shrinkwrap\": null,\n  \"_spec\": \"axios@^0.18.0\",\n  \"_where\": \"C:\\\\Users\\\\Alex\\\\Documents\\\\workspace\\\\roy\\\\node_modules\\\\@alife\\\\s-request\",\n  \"author\": {\n    \"name\": \"Matt Zabriskie\"\n  },\n  \"browser\": {\n    \"./lib/adapters/http.js\": \"./lib/adapters/xhr.js\"\n  },\n  \"bugs\": {\n    \"url\": \"https://github.com/axios/axios/issues\"\n  },\n  \"bundlesize\": [\n    {\n      \"path\": \"./dist/axios.min.js\",\n      \"threshold\": \"5kB\"\n    }\n  ],\n  \"dependencies\": {\n    \"follow-redirects\": \"^1.3.0\",\n    \"is-buffer\": \"^1.1.5\"\n  },\n  \"description\": \"Promise based HTTP client for the browser and node.js\",\n  \"devDependencies\": {\n    \"bundlesize\": \"^0.5.7\",\n    \"coveralls\": \"^2.11.9\",\n    \"es6-promise\": \"^4.0.5\",\n    \"grunt\": \"^1.0.1\",\n    \"grunt-banner\": \"^0.6.0\",\n    \"grunt-cli\": \"^1.2.0\",\n    \"grunt-contrib-clean\": \"^1.0.0\",\n    \"grunt-contrib-nodeunit\": \"^1.0.0\",\n    \"grunt-contrib-watch\": \"^1.0.0\",\n    \"grunt-eslint\": \"^19.0.0\",\n    \"grunt-karma\": \"^2.0.0\",\n    \"grunt-ts\": \"^6.0.0-beta.3\",\n    \"grunt-webpack\": \"^1.0.18\",\n    \"istanbul-instrumenter-loader\": \"^1.0.0\",\n    \"jasmine-core\": \"^2.4.1\",\n    \"karma\": \"^1.3.0\",\n    \"karma-chrome-launcher\": \"^2.0.0\",\n    \"karma-coverage\": \"^1.0.0\",\n    \"karma-firefox-launcher\": \"^1.0.0\",\n    \"karma-jasmine\": \"^1.0.2\",\n    \"karma-jasmine-ajax\": \"^0.1.13\",\n    \"karma-opera-launcher\": \"^1.0.0\",\n    \"karma-safari-launcher\": \"^1.0.0\",\n    \"karma-sauce-launcher\": \"^1.1.0\",\n    \"karma-sinon\": \"^1.0.5\",\n    \"karma-sourcemap-loader\": \"^0.3.7\",\n    \"karma-webpack\": \"^1.7.0\",\n    \"load-grunt-tasks\": \"^3.5.2\",\n    \"minimist\": \"^1.2.0\",\n    \"sinon\": \"^1.17.4\",\n    \"typescript\": \"^2.0.3\",\n    \"url-search-params\": \"^0.6.1\",\n    \"webpack\": \"^1.13.1\",\n    \"webpack-dev-server\": \"^1.14.1\"\n  },\n  \"directories\": {},\n  \"dist\": {\n    \"shasum\": \"32d53e4851efdc0a11993b6cd000789d70c05102\",\n    \"size\": 81711,\n    \"noattachment\": false,\n    \"key\": \"axios/-/axios-0.18.0.tgz\",\n    \"tarball\": \"http://registry.npm.alibaba-inc.com/axios/download/axios-0.18.0.tgz\"\n  },\n  \"gitHead\": \"d59c70fdfd35106130e9f783d0dbdcddd145b58f\",\n  \"homepage\": \"https://github.com/axios/axios\",\n  \"keywords\": [\n    \"xhr\",\n    \"http\",\n    \"ajax\",\n    \"promise\",\n    \"node\"\n  ],\n  \"license\": \"MIT\",\n  \"main\": \"index.js\",\n  \"maintainers\": [\n    {\n      \"name\": \"mzabriskie\",\n      \"email\": \"mzabriskie@gmail.com\"\n    },\n    {\n      \"name\": \"nickuraltsev\",\n      \"email\": \"nick.uraltsev@gmail.com\"\n    }\n  ],\n  \"name\": \"axios\",\n  \"optionalDependencies\": {},\n  \"publish_time\": 1519082934151,\n  \"readme\": \"ERROR: No README data found!\",\n  \"repository\": {\n    \"type\": \"git\",\n    \"url\": \"git+https://github.com/axios/axios.git\"\n  },\n  \"scripts\": {\n    \"build\": \"NODE_ENV=production grunt build\",\n    \"coveralls\": \"cat coverage/lcov.info | ./node_modules/coveralls/bin/coveralls.js\",\n    \"examples\": \"node ./examples/server.js\",\n    \"postversion\": \"git push && git push --tags\",\n    \"preversion\": \"npm test\",\n    \"start\": \"node ./sandbox/server.js\",\n    \"test\": \"grunt test && bundlesize\",\n    \"version\": \"npm run build && grunt version && git add -A dist && git add CHANGELOG.md bower.json package.json\"\n  },\n  \"typings\": \"./index.d.ts\",\n  \"version\": \"0.18.0\"\n}\n;"},"hash":"0269fb4958399e217d8329074103dd42","cacheData":{"env":{}}}